vrsix-0.2.0.dist-info/METADATA
vrsix-0.2.0.dist-info/WHEEL
vrsix-0.2.0.dist-info/entry_points.txt
vrsix-0.2.0.dist-info/licenses/LICENSE
vrsix.libs/libgcc_s-e52197c3.so.1
vrsix/cli.py
vrsix/load.py
vrsix/__init__.py
vrsix/sqlite.py
vrsix/_core.abi3.so
vrsix-0.2.0.dist-info/RECORD
