Metadata-Version: 2.4
Name: vrsix
Version: 0.2.0
Classifier: Development Status :: 3 - Alpha
Classifier: Programming Language :: Rust
Classifier: Programming Language :: Python
Classifier: Programming Language :: Python :: 3
Classifier: Programming Language :: Python :: 3 :: Only
Classifier: Programming Language :: Python :: 3.10
Classifier: Programming Language :: Python :: 3.11
Classifier: Programming Language :: Python :: 3.12
Classifier: Programming Language :: Python :: 3.13
Classifier: Topic :: Scientific/Engineering :: Bio-Informatics
Classifier: Intended Audience :: Science/Research
Classifier: License :: OSI Approved :: MIT License
Requires-Dist: click
Requires-Dist: asyncclick
Requires-Dist: pytest ; extra == 'tests'
Requires-Dist: pytest-cov ; extra == 'tests'
Requires-Dist: maturin ; extra == 'dev'
Requires-Dist: ruff==0.8.6 ; extra == 'dev'
Requires-Dist: pre-commit>=4.0.1 ; extra == 'dev'
Provides-Extra: tests
Provides-Extra: dev
License-File: LICENSE
Summary: Tools for indexing GREGoR VCFs
Author: James Stevenson
Requires-Python: >=3.10
Project-URL: Homepage, https://github.com/genomicmedlab/gregor
Project-URL: Documentation, https://github.com/genomicmedlab/gregor
Project-URL: Changelog, https://github.com/genomicmedlab/gregor/releases
Project-URL: Source, https://github.com/genomicmedlab/gregor
Project-URL: Bug Tracker, https://github.com/genomicmedlab/gregor/issues
